starlette_flask/__about__.py
starlette_flask/__init__.py
starlette_flask/middleware/__init__.py
starlette_flask/middleware/sessions.py
starlette_flask-0.1.0.dist-info/METADATA
starlette_flask-0.1.0.dist-info/WHEEL
starlette_flask-0.1.0.dist-info/licenses/LICENSE
starlette_flask-0.1.0.dist-info/RECORD
