Metadata-Version: 2.4
Name: starlette-flask
Version: 0.1.0
Summary: Session Middleware for Starlette/FastAPI Applications based on Flask Session Decoding and Encoding.
Project-URL: Changelog, https://github.com/hasansezertasan/starlette-flask/releases
Project-URL: Documentation, https://github.com/hasansezertasan/starlette-flask#readme
Project-URL: Issues, https://github.com/hasansezertasan/starlette-flask/issues
Project-URL: Source, https://github.com/hasansezertasan/starlette-flask
Author-email: hasansezertasan <hasansezertasan@gmail.com>
Maintainer-email: hasansezertasan <hasansezertasan@gmail.com>
License-Expression: MIT
License-File: LICENSE
Keywords: asgi,cookie,fastapi,flask,session,starlette
Classifier: Development Status :: 7 - Inactive
Classifier: Environment :: Web Environment
Classifier: Framework :: FastAPI
Classifier: Framework :: Flask
Classifier: Intended Audience :: Developers
Classifier: License :: OSI Approved :: MIT License
Classifier: Operating System :: OS Independent
Classifier: Programming Language :: Python
Classifier: Programming Language :: Python :: 3
Classifier: Programming Language :: Python :: 3 :: Only
Classifier: Programming Language :: Python :: 3.8
Classifier: Programming Language :: Python :: 3.9
Classifier: Programming Language :: Python :: 3.10
Classifier: Programming Language :: Python :: 3.11
Classifier: Programming Language :: Python :: 3.12
Classifier: Topic :: Internet
Classifier: Topic :: Internet :: WWW/HTTP :: Session
Classifier: Topic :: Internet :: WWW/HTTP :: WSGI
Classifier: Topic :: Internet :: WWW/HTTP :: WSGI :: Application
Classifier: Topic :: Software Development :: Libraries :: Application Frameworks
Classifier: Topic :: Software Development :: Libraries :: Python Modules
Classifier: Typing :: Typed
Requires-Python: >=3.8
Requires-Dist: starlette
